{
    "os": "Linux-5.4.0-117-generic-x86_64-with-debian-bullseye-sid",
    "python": "3.7.13",
    "heartbeatAt": "2022-07-23T20:12:22.242809",
    "startedAt": "2022-07-23T20:12:20.778170",
    "docker": null,
    "gpu": "NVIDIA GeForce RTX 2080 Ti",
    "gpu_count": 8,
    "cpu_count": 112,
    "cuda": null,
    "args": [
        "--alpha=0.1",
        "--batch_size=128",
        "--fanout=100"
    ],
    "state": "running",
    "program": "train.py",
    "codePath": "train.py",
    "git": {
        "remote": "git@github.com:KellyGong/fraud-detection-icdm.git",
        "commit": "d9dabcdb535d520758f3c31a485660365507d4d1"
    },
    "email": "864737851@qq.com",
    "root": "/data/zzh/gz/fraud-detection-icdm",
    "host": "wtf",
    "username": "zzh",
    "executable": "/data/zzh/anaconda3/envs/graph_pyg/bin/python"
}
